visitors/__init__.py
visitors/admin.py
visitors/apps.py
visitors/decorators.py
visitors/exceptions.py
visitors/forms.py
visitors/middleware.py
visitors/migrations/0001_initial.py
visitors/migrations/0002_visitorlog.py
visitors/migrations/0003_visitor_is_active.py
visitors/migrations/0004_visitor_expires_at.py
visitors/migrations/0005_visitorlog_status_code.py
visitors/migrations/0006_alter_visitor_uuid.py
visitors/migrations/0007_visitor_session_expiry.py
visitors/migrations/__init__.py
visitors/models.py
visitors/session.py
visitors/settings.py
visitors/signals.py
visitors/templates/visitors/self_service_request.html
visitors/templates/visitors/self_service_success.html
visitors/urls.py
visitors/views.py
django_visitor_pass-1.2.dist-info/METADATA
django_visitor_pass-1.2.dist-info/WHEEL
django_visitor_pass-1.2.dist-info/licenses/LICENSE
django_visitor_pass-1.2.dist-info/RECORD
